data_catapult/__init__.py
data_catapult/core/__init__.py
data_catapult/core/fetcher.py
data_catapult/core/models.py
data_catapult/database/__init__.py
data_catapult/database/clickhouse.py
data_catapult/database/monetdb.py
data_catapult/database/postgres.py
data_catapult/mondrian/__init__.py
data_catapult/mondrian/schema.py
data_catapult-0.0.35.dist-info/LICENSE
data_catapult-0.0.35.dist-info/METADATA
data_catapult-0.0.35.dist-info/WHEEL
data_catapult-0.0.35.dist-info/top_level.txt
data_catapult-0.0.35.dist-info/RECORD
