Metadata-Version: 2.1
Name: data-catapult
Version: 0.0.35
Summary: Python bulk data loading ETL library
Home-page: https://github.com/Datawheel/catapult
Author: Jonathan Speiser
Author-email: jonathan@datawheel.us
License: UNKNOWN
Platform: UNKNOWN
Classifier: Programming Language :: Python :: 3
Classifier: License :: OSI Approved :: MIT License
Classifier: Operating System :: OS Independent
Requires-Dist: clickhouse-driver (==0.1.1)
Requires-Dist: sqlalchemy (==1.2.10)
Requires-Dist: psycopg2-binary (==2.8.4)
Requires-Dist: pyyaml
Requires-Dist: dw-python-monetdb-async
Requires-Dist: pandas (==1.1.4)
Requires-Dist: requests
